h5py_wrapper/__init__.py
h5py_wrapper/lib.py
h5py_wrapper/wrapper.py
h5py_wrapper-1.1.0.data/scripts/convert_h5file
h5py_wrapper-1.1.0.dist-info/DESCRIPTION.rst
h5py_wrapper-1.1.0.dist-info/METADATA
h5py_wrapper-1.1.0.dist-info/RECORD
h5py_wrapper-1.1.0.dist-info/WHEEL
h5py_wrapper-1.1.0.dist-info/metadata.json
h5py_wrapper-1.1.0.dist-info/top_level.txt
tests/__init__.py
tests/test_wrapper.py
