Metadata-Version: 2.0
Name: h5py-wrapper
Version: 1.1.0
Summary: A wrapper to conveniently store nested Python dictionaries in hdf5 files.
Home-page: https://github.com/INM-6/h5py_wrapper
Author: Maximilian Schmidt, Jakob Jordan
Author-email: max.schmidt@fz-juelich.de
License: GPL2
Keywords: hdf5 h5py
Platform: UNKNOWN
Classifier: Development Status :: 4 - Beta
Classifier: License :: OSI Approved :: GNU General Public License v2 (GPLv2)
Classifier: Natural Language :: English
Classifier: Operating System :: OS Independent
Classifier: Programming Language :: Python :: 2.7
Classifier: Programming Language :: Python :: 3
Classifier: Programming Language :: Python :: 3.5
Classifier: Programming Language :: Python :: 3.6
Classifier: Topic :: Utilities
Requires-Python: >=2.7,!=3.0.*,!=3.1.*,!=3.2.*,!=3.3.*, !=3.4.*, <4
Requires-Dist: future
Requires-Dist: h5py
Requires-Dist: pytest-runner
